{
  "player": {
      "id": 1,
      "hand": {
          "cards": [
              {
                  "color": "RED",
                  "value": 2
              },
              {
                  "color": "YELLOW",
                  "value": 1
              },
              {
                  "color": "ORANGE",
                  "value": 7
              },
              {
                  "color": "VIOLET",
                  "value": 7
              },
              {
                  "color": "INDIGO",
                  "value": 3
              },
              {
                  "color": "INDIGO",
                  "value": 5
              },
              {
                  "color": "LIGHTBLUE",
                  "value": 2
              }
          ]
      },
      "palette": {
          "cards": [
              {
                  "color": "GREEN",
                  "value": 5
              }
          ]
      },
      "active": true
  },
  "game": {
      "id": "tiger11",
      "number_of_players": 2,
      "deck": {
          "cards": [
              {
                  "color": "RED",
                  "value": 1
              },
              {
                  "color": "INDIGO",
                  "value": 4
              },
              {
                  "color": "ORANGE",
                  "value": 1
              },
              {
                  "color": "VIOLET",
                  "value": 5
              },
              {
                  "color": "LIGHTBLUE",
                  "value": 5
              },
              {
                  "color": "YELLOW",
                  "value": 3
              },
              {
                  "color": "VIOLET",
                  "value": 4
              },
              {
                  "color": "GREEN",
                  "value": 7
              },
              {
                  "color": "GREEN",
                  "value": 3
              },
              {
                  "color": "LIGHTBLUE",
                  "value": 3
              },
              {
                  "color": "GREEN",
                  "value": 4
              },
              {
                  "color": "ORANGE",
                  "value": 5
              },
              {
                  "color": "INDIGO",
                  "value": 1
              },
              {
                  "color": "LIGHTBLUE",
                  "value": 4
              },
              {
                  "color": "VIOLET",
                  "value": 1
              },
              {
                  "color": "LIGHTBLUE",
                  "value": 6
              },
              {
                  "color": "GREEN",
                  "value": 6
              },
              {
                  "color": "INDIGO",
                  "value": 7
              },
              {
                  "color": "VIOLET",
                  "value": 6
              },
              {
                  "color": "LIGHTBLUE",
                  "value": 1
              },
              {
                  "color": "RED",
                  "value": 3
              },
              {
                  "color": "RED",
                  "value": 5
              },
              {
                  "color": "INDIGO",
                  "value": 2
              },
              {
                  "color": "GREEN",
                  "value": 2
              },
              {
                  "color": "YELLOW",
                  "value": 7
              },
              {
                  "color": "RED",
                  "value": 6
              },
              {
                  "color": "LIGHTBLUE",
                  "value": 7
              },
              {
                  "color": "ORANGE",
                  "value": 2
              },
              {
                  "color": "YELLOW",
                  "value": 2
              },
              {
                  "color": "YELLOW",
                  "value": 5
              },
              {
                  "color": "VIOLET",
                  "value": 2
              },
              {
                  "color": "ORANGE",
                  "value": 3
              },
              {
                  "color": "INDIGO",
                  "value": 6
              }
          ]
      },
      "canvas": {
          "card": {
              "color": "RED",
              "value": "S"
          }
      },
      "player_counter": 0,
      "players_ids": [
          0,
          1
      ]
  }
}
